outpost24hiabclient/__init__.py
outpost24hiabclient/clients/__init__.py
outpost24hiabclient/clients/hiabclient.py
outpost24hiabclient/entities/__init__.py
outpost24hiabclient/entities/scanner.py
outpost24hiabclient/entities/target.py
outpost24hiabclient/entities/targetgroup.py
outpost24hiabclient/entities/targets_tree.py
outpost24hiabclient/entities/user.py
outpost24hiabclient/entities/usergroup.py
outpost24hiabclient/exceptions/__init__.py
outpost24hiabclient/exceptions/exceptions.py
outpost24hiabclient/services/__init__.py
outpost24hiabclient/services/scanner_service.py
outpost24hiabclient/services/target_service.py
outpost24hiabclient/services/user_service.py
outpost24hiabclient/tools/__init__.py
outpost24hiabclient/tools/log.py
outpost24hiabclient/tools/xmltools.py
outpost24hiabclient-0.3.data/data/.VERSION
outpost24hiabclient-0.3.data/data/AUTHORS.rst
outpost24hiabclient-0.3.data/data/CONTRIBUTING.rst
outpost24hiabclient-0.3.data/data/HISTORY.rst
outpost24hiabclient-0.3.data/data/LICENSE
outpost24hiabclient-0.3.data/data/Pipfile
outpost24hiabclient-0.3.data/data/README.rst
outpost24hiabclient-0.3.data/data/USAGE.rst
outpost24hiabclient-0.3.data/data/dev-requirements.txt
outpost24hiabclient-0.3.data/data/requirements.txt
outpost24hiabclient-0.3.dist-info/AUTHORS.rst
outpost24hiabclient-0.3.dist-info/LICENSE
outpost24hiabclient-0.3.dist-info/METADATA
outpost24hiabclient-0.3.dist-info/WHEEL
outpost24hiabclient-0.3.dist-info/entry_points.txt
outpost24hiabclient-0.3.dist-info/top_level.txt
outpost24hiabclient-0.3.dist-info/RECORD
